setup.py
fmovice/__init__.py
fmovice/movice.py
fmovice.egg-info/PKG-INFO
fmovice.egg-info/SOURCES.txt
fmovice.egg-info/dependency_links.txt
fmovice.egg-info/entry_points.txt
fmovice.egg-info/requires.txt
fmovice.egg-info/top_level.txt