Metadata-Version: 1.0
Name: fmovice
Version: 0.0.4
Summary: 输入关键词搜索两大百度网盘提供商中的电影资源
Home-page: https://zhuanlan.zhihu.com/passer
Author: passer
Author-email: 904727147@qq.com
License: UNKNOWN
Platform: UNKNOWN
